yurt/__init__.py
yurt/yurt_core/__init__.py
yurt/yurt_core/add.py
yurt/yurt_core/cli.py
yurt/yurt_core/machine_share.py
yurt/yurt_core/provision.py
yurt/yurt_core/setup.py
yurt/yurt_core/utils.py
yurt/yurt_core/env/__init__.py
yurt/yurt_core/env/commands.py
yurt/yurt_core/env/helpers.py
yurt/yurt_core/tests/__init__.py
yurt/yurt_core/tests/base.py
yurt/yurt_core/tests/env_test.py
yurt/yurt_core/tests/fixtures.py
yurt/yurt_core/tests/machine_share_test.py
yurt/yurt_core/tests/provision_test.py
yurt/yurt_core/tests/setup_test.py
yurt/yurt_core/tests/utils.py
yak_yurt-1.0.0.dist-info/METADATA
yak_yurt-1.0.0.dist-info/WHEEL
yak_yurt-1.0.0.dist-info/entry_points.txt
yak_yurt-1.0.0.dist-info/top_level.txt
yak_yurt-1.0.0.dist-info/RECORD
