Metadata-Version: 2.1
Name: yak-yurt
Version: 1.0.0
Summary: A tool for deploying Django Web Apps to remote servers
Home-page: https://github.com/yeti/yurt/
Author: Dean Mercado
Author-email: support@yeti.co
License: MIT
Platform: UNKNOWN
Classifier: Development Status :: 3 - Alpha
Classifier: Environment :: Console
Classifier: Intended Audience :: Developers
Classifier: Programming Language :: Python
Classifier: Programming Language :: Python :: 2
Classifier: Programming Language :: Python :: 2.7
Classifier: Programming Language :: Python :: 3.4
Classifier: Programming Language :: Python :: 3.5
Classifier: Topic :: Software Development
Classifier: Topic :: Software Development :: Build Tools
Classifier: Topic :: Software Development :: Libraries :: Python Modules
Requires-Dist: click (==6.6)
Requires-Dist: PyYAML (==3.12)
Requires-Dist: cookiecutter (==1.6.0)
Requires-Dist: invoke (==1.1.0)
Requires-Dist: colorama (==0.3.9)
